pnap_network_storage_api/__init__.py
pnap_network_storage_api/api_client.py
pnap_network_storage_api/api_response.py
pnap_network_storage_api/configuration.py
pnap_network_storage_api/exceptions.py
pnap_network_storage_api/py.typed
pnap_network_storage_api/rest.py
pnap_network_storage_api/version.py
pnap_network_storage_api/api/__init__.py
pnap_network_storage_api/api/storage_networks_api.py
pnap_network_storage_api/models/__init__.py
pnap_network_storage_api/models/error.py
pnap_network_storage_api/models/nfs_permissions.py
pnap_network_storage_api/models/nfs_permissions_create.py
pnap_network_storage_api/models/nfs_permissions_update.py
pnap_network_storage_api/models/permissions.py
pnap_network_storage_api/models/permissions_create.py
pnap_network_storage_api/models/permissions_update.py
pnap_network_storage_api/models/status.py
pnap_network_storage_api/models/storage_network.py
pnap_network_storage_api/models/storage_network_create.py
pnap_network_storage_api/models/storage_network_update.py
pnap_network_storage_api/models/storage_network_volume_create.py
pnap_network_storage_api/models/tag_assignment.py
pnap_network_storage_api/models/tag_assignment_request.py
pnap_network_storage_api/models/volume.py
pnap_network_storage_api/models/volume_create.py
pnap_network_storage_api/models/volume_update.py
pnap_network_storage_api-2.0.4.dist-info/METADATA
pnap_network_storage_api-2.0.4.dist-info/WHEEL
pnap_network_storage_api-2.0.4.dist-info/top_level.txt
pnap_network_storage_api-2.0.4.dist-info/RECORD
